paramga/__init__.py
paramga/crossover.py
paramga/demo.py
paramga/encoding.py
paramga/generator.py
paramga/iteration_state.py
paramga/main.py
paramga/mutation.py
paramga/plot.py
paramga/random_helpers.py
paramga/run.py
paramga/types.py
paramga/version.py
paramga/loss_functions/__init__.py
paramga/loss_functions/rmse.py
paramga/loss_functions/rmse_test.py
paramga/loss_functions/rsquared.py
paramga/loss_functions/rsquared_test.py
paramga/loss_functions/testing_utils.py
paramga/post_processing/__init__.py
paramga/post_processing/normalize_outputs.py
paramga/post_processing/scaling_functions.py
tests/__init__.py
tests/data_sampling_test.py
tests/mutation_test.py
tests/objects_test.py
tests/run_test.py
paramga-0.5.5.dist-info/METADATA
paramga-0.5.5.dist-info/WHEEL
paramga-0.5.5.dist-info/top_level.txt
paramga-0.5.5.dist-info/RECORD
