Metadata-Version: 2.1
Name: paramga
Version: 0.5.5
Summary: Parameter Regression GA tool
Author: SBland
Author-email: sblandcouk@gmail.com
Keywords: genetic algorithm,optimization,scientific modelling
Classifier: Programming Language :: Python :: 3.8
Classifier: Operating System :: OS Independent
Classifier: License :: OSI Approved :: MIT License
Requires-Python: >=3.6
Requires-Dist: numpy
Provides-Extra: test
Requires-Dist: pytest ; extra == 'test'
Requires-Dist: numpy ; extra == 'test'
